{
  "id": "zone-intro",
  "title": "Namtara Zone Title Popup",
  "description": "FromSoft-style zone popup with sound, tied to Scenes and triggered manually via chat command.",
  "version": "1.0.0",
  "compatibility": {
    "minimum": "11",
    "verified": "11"
  },
  "scripts": [
    "scripts/zone-title.js"
  ],
  "esmodules": [],
  "styles": [],
  "packs": [],
  "languages": [],
  "url": "https://github.com/FerrellFT/Zone-Intro",
  "manifest": "https://raw.githubusercontent.com/FerrellFT/Zone-Intro/main/module.json",
  "download": "https://github.com/FerrellFT/Zone-Intro/archive/refs/heads/main.zip",
  "authors": [
    {
      "name": "Time Runs Out",
      "url": "https://github.com/FerrellFT",
      "email": ""
    }
  ]
}
